LICENSE
MANIFEST.in
README.rst
setup.py
mailsink/__init__.py
mailsink/handler.py
mailsink/server.py
mailsink/webui.py
mailsink.egg-info/PKG-INFO
mailsink.egg-info/SOURCES.txt
mailsink.egg-info/dependency_links.txt
mailsink.egg-info/entry_points.txt
mailsink.egg-info/requires.txt
mailsink.egg-info/top_level.txt
mailsink.egg-info/zip-safe
mailsink/static/index.html
mailsink/static/jquery-1.4.4.min.js
mailsink/static/mail16.ico
mailsink/static/mail512.png
mailsink/static/sink.css
mailsink/static/sink.js