Metadata-Version: 1.0
Name: mailsink
Version: 0.0.2
Summary: a mock SMTP server
Home-page: http://github.com/bgilmore/mailsink
Author: Brandon Gilmore
Author-email: brandon@mg2.org
License: BSD
Platform: any
Classifier: Development Status :: 2 - Pre-Alpha
Classifier: Environment :: Web Environment
Classifier: Framework :: Twisted
Classifier: Intended Audience :: Developers
Classifier: License :: OSI Approved :: BSD License
Classifier: Topic :: Communications :: Email
Classifier: Topic :: Software Development :: Testing
